{"v":"5.7.4","fr":30,"ip":0,"op":120,"w":375,"h":650,"nm":"bg_effect_android","ddd":0,"assets":[{"id":"comp_0","layers":[{"ddd":0,"ind":1,"ty":0,"nm":"BG_Effect_Source_Lottie_Android","refId":"comp_1","sr":1,"ks":{"o":{"a":0,"k":96,"ix":11},"r":{"a":0,"k":0,"ix":10},"p":{"a":0,"k":[375,1420,0],"ix":2,"l":2},"a":{"a":0,"k":[375,1624,0],"ix":1,"l":2},"s":{"a":0,"k":[100,100,100],"ix":6,"l":2}},"ao":0,"ef":[{"ty":29,"nm":"Gaussian Blur","np":5,"mn":"ADBE Gaussian Blur 2","ix":1,"en":1,"ef":[{"ty":0,"nm":"Blurriness","mn":"ADBE Gaussian Blur 2-0001","ix":1,"v":{"a":0,"k":300,"ix":1}},{"ty":7,"nm":"Blur Dimensions","mn":"ADBE Gaussian Blur 2-0002","ix":2,"v":{"a":0,"k":1,"ix":2}},{"ty":7,"nm":"Repeat Edge Pixels","mn":"ADBE Gaussian Blur 2-0003","ix":3,"v":{"a":0,"k":1,"ix":3}}]}],"w":750,"h":1624,"ip":0,"op":120,"st":0,"bm":0}]},{"id":"comp_1","layers":[{"ddd":0,"ind":1,"ty":3,"nm":"control_01","sr":1,"ks":{"o":{"a":0,"k":0,"ix":11},"r":{"a":0,"k":0,"ix":10},"p":{"s":true,"x":{"a":0,"k":240,"ix":3},"y":{"a":0,"k":1020,"ix":4}},"a":{"a":0,"k":[0,0,0],"ix":1,"l":2},"s":{"a":0,"k":[100,100,100],"ix":6,"l":2}},"ao":0,"ip":0,"op":300,"st":0,"bm":0},{"ddd":0,"ind":2,"ty":3,"nm":"control_01_xPos","parent":1,"sr":1,"ks":{"o":{"a":0,"k":0,"ix":11},"r":{"a":0,"k":0,"ix":10},"p":{"s":true,"x":{"a":1,"k":[{"i":{"x":[0.65],"y":[1]},"o":{"x":[0.35],"y":[0]},"t":0,"s":[-80]},{"i":{"x":[0.65],"y":[1]},"o":{"x":[0.35],"y":[0]},"t":30,"s":[60]},{"i":{"x":[0.65],"y":[1]},"o":{"x":[0.35],"y":[0]},"t":60,"s":[-80]},{"i":{"x":[0.65],"y":[1]},"o":{"x":[0.35],"y":[0]},"t":90,"s":[60]},{"t":120,"s":[-80]}],"ix":3},"y":{"a":0,"k":0,"ix":4}},"a":{"a":0,"k":[0,0,0],"ix":1,"l":2},"s":{"a":0,"k":[100,100,100],"ix":6,"l":2}},"ao":0,"ip":0,"op":300,"st":0,"bm":0},{"ddd":0,"ind":3,"ty":4,"nm":"circle_01","parent":2,"sr":1,"ks":{"o":{"a":0,"k":100,"ix":11},"r":{"a":1,"k":[{"i":{"x":[0.65],"y":[1]},"o":{"x":[0.35],"y":[0]},"t":0,"s":[22]},{"i":{"x":[0.65],"y":[1]},"o":{"x":[0.35],"y":[0]},"t":30,"s":[42]},{"i":{"x":[0.65],"y":[1]},"o":{"x":[0.35],"y":[0]},"t":60,"s":[22]},{"i":{"x":[0.65],"y":[1]},"o":{"x":[0.35],"y":[0]},"t":90,"s":[42]},{"t":120,"s":[22]}],"ix":10},"p":{"a":1,"k":[{"i":{"x":0.833,"y":0.785},"o":{"x":0.167,"y":0.167},"t":0,"s":[43.019,3.784,0],"to":[-1.537,-0.178,0],"ti":[1.889,2.676,0]},{"i":{"x":0.833,"y":0.802},"o":{"x":0.167,"y":0.136},"t":6,"s":[33.796,2.716,0],"to":[-1.889,-2.676,0],"ti":[-0.414,5.926,0]},{"i":{"x":0.833,"y":0.841},"o":{"x":0.167,"y":0.144},"t":12,"s":[31.687,-12.273,0],"to":[0.414,-5.926,0],"ti":[-1.513,6.51,0]},{"i":{"x":0.833,"y":0.834},"o":{"x":0.167,"y":0.176},"t":18,"s":[36.282,-32.838,0],"to":[1.513,-6.51,0],"ti":[-1.126,6.219,0]},{"i":{"x":0.833,"y":0.838},"o":{"x":0.167,"y":0.167},"t":24,"s":[40.768,-51.335,0],"to":[1.126,-6.219,0],"ti":[-0.054,6.102,0]},{"i":{"x":0.833,"y":0.842},"o":{"x":0.167,"y":0.171},"t":30,"s":[43.041,-70.155,0],"to":[0.054,-6.102,0],"ti":[1.435,5.401,0]},{"i":{"x":0.833,"y":0.842},"o":{"x":0.167,"y":0.176},"t":36,"s":[41.09,-87.945,0],"to":[-1.435,-5.401,0],"ti":[2.8,4.093,0]},{"i":{"x":0.833,"y":0.835},"o":{"x":0.167,"y":0.177},"t":42,"s":[34.433,-102.56,0],"to":[-2.8,-4.093,0],"ti":[3.932,1.465,0]},{"i":{"x":0.833,"y":0.771},"o":{"x":0.167,"y":0.169},"t":48,"s":[24.29,-112.501,0],"to":[-3.932,-1.465,0],"ti":[4.913,-3.261,0]},{"i":{"x":0.833,"y":0.807},"o":{"x":0.167,"y":0.131},"t":54,"s":[10.838,-111.352,0],"to":[-4.913,3.261,0],"ti":[4.716,-8.029,0]},{"i":{"x":0.833,"y":0.84},"o":{"x":0.167,"y":0.147},"t":60,"s":[-5.19,-92.936,0],"to":[-4.716,8.029,0],"ti":[2.651,-9.832,0]},{"i":{"x":0.833,"y":0.859},"o":{"x":0.167,"y":0.174},"t":66,"s":[-17.455,-63.179,0],"to":[-2.651,9.832,0],"ti":[-0.508,-8.024,0]},{"i":{"x":0.833,"y":0.85},"o":{"x":0.167,"y":0.204},"t":72,"s":[-21.095,-33.942,0],"to":[0.508,8.024,0],"ti":[-3.658,-3.682,0]},{"i":{"x":0.833,"y":0.809},"o":{"x":0.167,"y":0.188},"t":78,"s":[-14.404,-15.034,0],"to":[3.658,3.682,0],"ti":[-5.502,1.306,0]},{"i":{"x":0.833,"y":0.855},"o":{"x":0.167,"y":0.148},"t":84,"s":[0.851,-11.852,0],"to":[5.502,-1.306,0],"ti":[-4.688,3.743,0]},{"i":{"x":0.833,"y":0.876},"o":{"x":0.167,"y":0.196},"t":90,"s":[18.605,-22.872,0],"to":[4.688,-3.743,0],"ti":[-2.821,1.665,0]},{"i":{"x":0.833,"y":0.773},"o":{"x":0.167,"y":0.256},"t":96,"s":[28.981,-34.31,0],"to":[2.821,-1.665,0],"ti":[-1.937,-2.212,0]},{"i":{"x":0.833,"y":0.822},"o":{"x":0.167,"y":0.132},"t":102,"s":[35.531,-32.862,0],"to":[1.937,2.212,0],"ti":[-1.301,-4.374,0]},{"i":{"x":0.833,"y":0.858},"o":{"x":0.167,"y":0.157},"t":108,"s":[40.605,-21.037,0],"to":[1.301,4.374,0],"ti":[-0.402,-4.137,0]},{"i":{"x":0.833,"y":0.833},"o":{"x":0.167,"y":0.201},"t":114,"s":[43.339,-6.617,0],"to":[0.402,4.137,0],"ti":[0.053,-1.733,0]},{"t":120,"s":[43.019,3.784,0]}],"ix":2,"l":2},"a":{"a":0,"k":[0,0,0],"ix":1,"l":2},"s":{"a":0,"k":[100,100,100],"ix":6,"l":2}},"ao":0,"ef":[{"ty":5,"nm":"wiggle_01","np":3,"mn":"ADBE Slider Control","ix":1,"en":1,"ef":[{"ty":0,"nm":"Slider","mn":"ADBE Slider Control-0001","ix":1,"v":{"a":0,"k":0.8,"ix":1}}]},{"ty":5,"nm":"wiggle_02","np":3,"mn":"ADBE Slider Control","ix":2,"en":1,"ef":[{"ty":0,"nm":"Slider","mn":"ADBE Slider Control-0001","ix":1,"v":{"a":0,"k":140,"ix":1}}]}],"shapes":[{"ty":"gr","it":[{"d":1,"ty":"el","s":{"a":0,"k":[836,836],"ix":2},"p":{"a":0,"k":[0,0],"ix":3},"nm":"Ellipse Path 1","mn":"ADBE Vector Shape - Ellipse","hd":false},{"ty":"gf","o":{"a":0,"k":100,"ix":10},"r":1,"bm":0,"g":{"p":7,"k":{"a":0,"k":[0,0.353,1,0.843,0.165,0.322,0.88,0.818,0.33,0.29,0.761,0.792,0.495,0.231,0.594,0.857,0.66,0.173,0.427,0.922,0.83,0.169,0.425,0.922,1,0.165,0.424,0.922,0,0.2,0.165,0.45,0.33,0.7,0.495,0.7,0.66,0.7,0.83,0.85,1,1],"ix":9}},"s":{"a":0,"k":[-540,0],"ix":5},"e":{"a":0,"k":[540,0],"ix":6},"t":1,"nm":"Gradient Fill 1","mn":"ADBE Vector Graphic - G-Fill","hd":false},{"ty":"tr","p":{"a":0,"k":[0,0],"ix":2},"a":{"a":0,"k":[0,0],"ix":1},"s":{"a":0,"k":[100,100],"ix":3},"r":{"a":0,"k":0,"ix":6},"o":{"a":0,"k":100,"ix":7},"sk":{"a":0,"k":0,"ix":4},"sa":{"a":0,"k":0,"ix":5},"nm":"Transform"}],"nm":"Ellipse 1","np":2,"cix":2,"bm":0,"ix":1,"mn":"ADBE Vector Group","hd":false}],"ip":0,"op":300,"st":0,"bm":0},{"ddd":0,"ind":4,"ty":3,"nm":"control_02","sr":1,"ks":{"o":{"a":0,"k":0,"ix":11},"r":{"a":0,"k":0,"ix":10},"p":{"a":0,"k":[586,1370,0],"ix":2,"l":2},"a":{"a":0,"k":[0,0,0],"ix":1,"l":2},"s":{"a":0,"k":[100,100,100],"ix":6,"l":2}},"ao":0,"ip":0,"op":300,"st":0,"bm":0},{"ddd":0,"ind":5,"ty":4,"nm":"circle_02","parent":4,"sr":1,"ks":{"o":{"a":0,"k":100,"ix":11},"r":{"a":0,"k":-26,"ix":10},"p":{"a":1,"k":[{"i":{"x":0.833,"y":0.793},"o":{"x":0.167,"y":0.167},"t":0,"s":[119.323,83.469,0],"to":[-2.917,0.221,0],"ti":[6.944,1.397,0]},{"i":{"x":0.833,"y":0.815},"o":{"x":0.167,"y":0.14},"t":6,"s":[101.818,84.796,0],"to":[-6.944,-1.397,0],"ti":[7.961,5.182,0]},{"i":{"x":0.833,"y":0.823},"o":{"x":0.167,"y":0.152},"t":12,"s":[77.657,75.089,0],"to":[-7.961,-5.182,0],"ti":[7.066,8.648,0]},{"i":{"x":0.833,"y":0.832},"o":{"x":0.167,"y":0.158},"t":18,"s":[54.055,53.707,0],"to":[-7.066,-8.648,0],"ti":[5.1,10.819,0]},{"i":{"x":0.833,"y":0.844},"o":{"x":0.167,"y":0.165},"t":24,"s":[35.26,23.204,0],"to":[-5.1,-10.819,0],"ti":[2.675,11.011,0]},{"i":{"x":0.833,"y":0.859},"o":{"x":0.167,"y":0.178},"t":30,"s":[23.453,-11.21,0],"to":[-2.675,-11.011,0],"ti":[0.259,8.912,0]},{"i":{"x":0.833,"y":0.878},"o":{"x":0.167,"y":0.204},"t":36,"s":[19.213,-42.864,0],"to":[-0.259,-8.912,0],"ti":[-1.652,4.71,0]},{"i":{"x":0.833,"y":0.867},"o":{"x":0.167,"y":0.265},"t":42,"s":[21.9,-64.682,0],"to":[1.652,-4.71,0],"ti":[-1.656,0.3,0]},{"i":{"x":0.833,"y":0.756},"o":{"x":0.167,"y":0.223},"t":48,"s":[29.127,-71.125,0],"to":[1.656,-0.3,0],"ti":[0.075,-2.636,0]},{"i":{"x":0.833,"y":0.817},"o":{"x":0.167,"y":0.127},"t":54,"s":[31.837,-66.481,0],"to":[-0.075,2.636,0],"ti":[1.642,-3.91,0]},{"i":{"x":0.833,"y":0.838},"o":{"x":0.167,"y":0.153},"t":60,"s":[28.679,-55.312,0],"to":[-1.642,3.91,0],"ti":[2.282,-3.931,0]},{"i":{"x":0.833,"y":0.841},"o":{"x":0.167,"y":0.171},"t":66,"s":[21.987,-43.019,0],"to":[-2.282,3.931,0],"ti":[1.829,-3.766,0]},{"i":{"x":0.833,"y":0.838},"o":{"x":0.167,"y":0.175},"t":72,"s":[14.988,-31.725,0],"to":[-1.829,3.766,0],"ti":[0.287,-3.718,0]},{"i":{"x":0.833,"y":0.805},"o":{"x":0.167,"y":0.171},"t":78,"s":[11.013,-20.425,0],"to":[-0.287,3.718,0],"ti":[-2.149,-3.634,0]},{"i":{"x":0.833,"y":0.795},"o":{"x":0.167,"y":0.146},"t":84,"s":[13.268,-9.415,0],"to":[2.149,3.634,0],"ti":[-5.011,-3.639,0]},{"i":{"x":0.833,"y":0.815},"o":{"x":0.167,"y":0.14},"t":90,"s":[23.904,1.377,0],"to":[5.011,3.639,0],"ti":[-7.225,-4.046,0]},{"i":{"x":0.833,"y":0.827},"o":{"x":0.167,"y":0.151},"t":96,"s":[43.334,12.422,0],"to":[7.225,4.046,0],"ti":[-8,-5.034,0]},{"i":{"x":0.833,"y":0.837},"o":{"x":0.167,"y":0.161},"t":102,"s":[67.253,25.656,0],"to":[8,5.034,0],"ti":[-7.353,-6.153,0]},{"i":{"x":0.833,"y":0.851},"o":{"x":0.167,"y":0.17},"t":108,"s":[91.331,42.623,0],"to":[7.353,6.153,0],"ti":[-4.665,-6.808,0]},{"i":{"x":0.833,"y":0.833},"o":{"x":0.167,"y":0.189},"t":114,"s":[111.37,62.573,0],"to":[4.665,6.808,0],"ti":[-1.326,-3.483,0]},{"t":120,"s":[119.323,83.469,0]}],"ix":2,"l":2},"a":{"a":0,"k":[618,333,0],"ix":1,"l":2},"s":{"a":0,"k":[100,100,100],"ix":6,"l":2}},"ao":0,"ef":[{"ty":5,"nm":"wiggle_01","np":3,"mn":"ADBE Slider Control","ix":1,"en":1,"ef":[{"ty":0,"nm":"Slider","mn":"ADBE Slider Control-0001","ix":1,"v":{"a":0,"k":0.6,"ix":1}}]},{"ty":5,"nm":"wiggle_02","np":3,"mn":"ADBE Slider Control","ix":2,"en":1,"ef":[{"ty":0,"nm":"Slider","mn":"ADBE Slider Control-0001","ix":1,"v":{"a":0,"k":120,"ix":1}}]}],"shapes":[{"ty":"gr","it":[{"d":1,"ty":"el","s":{"a":0,"k":[1564,1564],"ix":2},"p":{"a":0,"k":[0,0],"ix":3},"nm":"Ellipse Path 1","mn":"ADBE Vector Shape - Ellipse","hd":false},{"ty":"gf","o":{"a":0,"k":100,"ix":10},"r":1,"bm":0,"g":{"p":7,"k":{"a":0,"k":[0.1,0.502,1,0.969,0.225,0.296,0.81,0.984,0.35,0.09,0.62,1,0.5,0.167,0.514,1,0.65,0.243,0.408,1,0.775,0.224,0.341,0.953,0.9,0.204,0.275,0.906,0.1,0.2,0.225,0.35,0.35,0.5,0.5,0.5,0.65,0.5,0.775,0.5,0.9,0.5],"ix":9}},"s":{"a":0,"k":[-720,0],"ix":5},"e":{"a":0,"k":[420,0],"ix":6},"t":2,"h":{"a":0,"k":0,"ix":7},"a":{"a":0,"k":0,"ix":8},"nm":"Gradient Fill 1","mn":"ADBE Vector Graphic - G-Fill","hd":false},{"ty":"tr","p":{"a":0,"k":[618,333],"ix":2},"a":{"a":0,"k":[0,0],"ix":1},"s":{"a":0,"k":[100,100],"ix":3},"r":{"a":0,"k":0,"ix":6},"o":{"a":0,"k":100,"ix":7},"sk":{"a":0,"k":0,"ix":4},"sa":{"a":0,"k":0,"ix":5},"nm":"Transform"}],"nm":"Ellipse 1","np":2,"cix":2,"bm":0,"ix":1,"mn":"ADBE Vector Group","hd":false}],"ip":0,"op":300,"st":0,"bm":0},{"ddd":0,"ind":6,"ty":3,"nm":"control_06","sr":1,"ks":{"o":{"a":0,"k":0,"ix":11},"r":{"a":0,"k":0,"ix":10},"p":{"a":0,"k":[880,1232,0],"ix":2,"l":2},"a":{"a":0,"k":[0,0,0],"ix":1,"l":2},"s":{"a":0,"k":[100,100,100],"ix":6,"l":2}},"ao":0,"ip":0,"op":300,"st":0,"bm":0},{"ddd":0,"ind":7,"ty":4,"nm":"circle_06","parent":6,"sr":1,"ks":{"o":{"a":0,"k":80,"ix":11},"r":{"a":0,"k":0,"ix":10},"p":{"a":1,"k":[{"i":{"x":0.833,"y":0.841},"o":{"x":0.167,"y":0.167},"t":0,"s":[-45.342,-62.526,0],"to":[-0.841,1.058,0],"ti":[1.34,-2.173,0]},{"i":{"x":0.833,"y":0.853},"o":{"x":0.167,"y":0.175},"t":6,"s":[-50.388,-56.175,0],"to":[-1.34,2.173,0],"ti":[0.495,-2.042,0]},{"i":{"x":0.833,"y":0.846},"o":{"x":0.167,"y":0.192},"t":12,"s":[-53.383,-49.486,0],"to":[-0.495,2.042,0],"ti":[-0.509,-1.512,0]},{"i":{"x":0.833,"y":0.832},"o":{"x":0.167,"y":0.182},"t":18,"s":[-53.357,-43.923,0],"to":[0.509,1.512,0],"ti":[-1.297,-0.602,0]},{"i":{"x":0.833,"y":0.804},"o":{"x":0.167,"y":0.166},"t":24,"s":[-50.329,-40.414,0],"to":[1.297,0.602,0],"ti":[-1.862,0.066,0]},{"i":{"x":0.833,"y":0.808},"o":{"x":0.167,"y":0.145},"t":30,"s":[-45.576,-40.311,0],"to":[1.862,-0.066,0],"ti":[-2.312,-0.567,0]},{"i":{"x":0.833,"y":0.781},"o":{"x":0.167,"y":0.147},"t":36,"s":[-39.157,-40.808,0],"to":[2.312,0.567,0],"ti":[-2.816,-2.336,0]},{"i":{"x":0.833,"y":0.807},"o":{"x":0.167,"y":0.134},"t":42,"s":[-31.707,-36.906,0],"to":[2.816,2.336,0],"ti":[-3.583,-3.957,0]},{"i":{"x":0.833,"y":0.828},"o":{"x":0.167,"y":0.147},"t":48,"s":[-22.263,-26.79,0],"to":[3.583,3.957,0],"ti":[-4.418,-4.402,0]},{"i":{"x":0.833,"y":0.841},"o":{"x":0.167,"y":0.162},"t":54,"s":[-10.206,-13.163,0],"to":[4.418,4.402,0],"ti":[-5.002,-3.437,0]},{"i":{"x":0.833,"y":0.827},"o":{"x":0.167,"y":0.176},"t":60,"s":[4.248,-0.379,0],"to":[5.002,3.437,0],"ti":[-5.281,-2.87,0]},{"i":{"x":0.833,"y":0.842},"o":{"x":0.167,"y":0.161},"t":66,"s":[19.803,7.461,0],"to":[5.281,2.87,0],"ti":[-4.906,-3.247,0]},{"i":{"x":0.833,"y":0.889},"o":{"x":0.167,"y":0.176},"t":72,"s":[35.932,16.842,0],"to":[4.906,3.247,0],"ti":[-2.926,-1.9,0]},{"i":{"x":0.833,"y":0.725},"o":{"x":0.167,"y":0.337},"t":78,"s":[49.237,26.943,0],"to":[2.926,1.9,0],"ti":[0.606,1.429,0]},{"i":{"x":0.833,"y":0.733},"o":{"x":0.167,"y":0.119},"t":84,"s":[53.49,28.243,0],"to":[-0.606,-1.429,0],"ti":[4.604,4.935,0]},{"i":{"x":0.833,"y":0.808},"o":{"x":0.167,"y":0.121},"t":90,"s":[45.601,18.372,0],"to":[-4.604,-4.935,0],"ti":[7.734,7.442,0]},{"i":{"x":0.833,"y":0.844},"o":{"x":0.167,"y":0.147},"t":96,"s":[25.868,-1.368,0],"to":[-7.734,-7.442,0],"ti":[8.213,7.852,0]},{"i":{"x":0.833,"y":0.876},"o":{"x":0.167,"y":0.179},"t":102,"s":[-0.804,-26.28,0],"to":[-8.213,-7.852,0],"ti":[5.452,5.604,0]},{"i":{"x":0.833,"y":0.85},"o":{"x":0.167,"y":0.256},"t":108,"s":[-23.41,-48.477,0],"to":[-5.452,-5.604,0],"ti":[3.655,2.341,0]},{"i":{"x":0.833,"y":0.833},"o":{"x":0.167,"y":0.188},"t":114,"s":[-33.518,-59.903,0],"to":[-3.655,-2.341,0],"ti":[1.971,0.437,0]},{"t":120,"s":[-45.342,-62.526,0]}],"ix":2,"l":2},"a":{"a":0,"k":[618,333,0],"ix":1,"l":2},"s":{"a":0,"k":[100,100,100],"ix":6,"l":2}},"ao":0,"ef":[{"ty":5,"nm":"wiggle_01","np":3,"mn":"ADBE Slider Control","ix":1,"en":1,"ef":[{"ty":0,"nm":"Slider","mn":"ADBE Slider Control-0001","ix":1,"v":{"a":0,"k":0.8,"ix":1}}]},{"ty":5,"nm":"wiggle_02","np":3,"mn":"ADBE Slider Control","ix":2,"en":1,"ef":[{"ty":0,"nm":"Slider","mn":"ADBE Slider Control-0001","ix":1,"v":{"a":0,"k":80,"ix":1}}]}],"shapes":[{"ty":"gr","it":[{"d":1,"ty":"el","s":{"a":0,"k":[460,460],"ix":2},"p":{"a":0,"k":[0,0],"ix":3},"nm":"Ellipse Path 1","mn":"ADBE Vector Shape - Ellipse","hd":false},{"ty":"fl","c":{"a":0,"k":[0.262745098039,0.956862745098,0.88745099236,1],"ix":4},"o":{"a":0,"k":100,"ix":5},"r":1,"bm":0,"nm":"Fill 1","mn":"ADBE Vector Graphic - Fill","hd":false},{"ty":"tr","p":{"a":0,"k":[618,333],"ix":2},"a":{"a":0,"k":[0,0],"ix":1},"s":{"a":0,"k":[100,100],"ix":3},"r":{"a":0,"k":0,"ix":6},"o":{"a":0,"k":100,"ix":7},"sk":{"a":0,"k":0,"ix":4},"sa":{"a":0,"k":0,"ix":5},"nm":"Transform"}],"nm":"Ellipse 1","np":2,"cix":2,"bm":0,"ix":1,"mn":"ADBE Vector Group","hd":false}],"ip":0,"op":300,"st":0,"bm":0},{"ddd":0,"ind":8,"ty":3,"nm":"control_05","sr":1,"ks":{"o":{"a":0,"k":0,"ix":11},"r":{"a":0,"k":0,"ix":10},"p":{"a":0,"k":[486,1370,0],"ix":2,"l":2},"a":{"a":0,"k":[0,0,0],"ix":1,"l":2},"s":{"a":0,"k":[100,100,100],"ix":6,"l":2}},"ao":0,"ip":0,"op":300,"st":0,"bm":0},{"ddd":0,"ind":9,"ty":4,"nm":"circle_05","parent":8,"sr":1,"ks":{"o":{"a":0,"k":100,"ix":11},"r":{"a":1,"k":[{"i":{"x":[0.833],"y":[0.833]},"o":{"x":[0.167],"y":[0.167]},"t":0,"s":[180]},{"t":120,"s":[540]}],"ix":10},"p":{"a":1,"k":[{"i":{"x":0.833,"y":0.83},"o":{"x":0.167,"y":0.167},"t":0,"s":[-60.776,4.842,0],"to":[2.338,-1.749,0],"ti":[-4.893,3.364,0]},{"i":{"x":0.833,"y":0.838},"o":{"x":0.167,"y":0.164},"t":6,"s":[-46.748,-5.653,0],"to":[4.893,-3.364,0],"ti":[-5.249,2.575,0]},{"i":{"x":0.833,"y":0.831},"o":{"x":0.167,"y":0.171},"t":12,"s":[-31.416,-15.345,0],"to":[5.249,-2.575,0],"ti":[-5.575,1.478,0]},{"i":{"x":0.833,"y":0.836},"o":{"x":0.167,"y":0.165},"t":18,"s":[-15.257,-21.103,0],"to":[5.575,-1.478,0],"ti":[-5.713,0.73,0]},{"i":{"x":0.833,"y":0.845},"o":{"x":0.167,"y":0.169},"t":24,"s":[2.036,-24.212,0],"to":[5.713,-0.73,0],"ti":[-5.259,0.311,0]},{"i":{"x":0.833,"y":0.859},"o":{"x":0.167,"y":0.181},"t":30,"s":[19.022,-25.481,0],"to":[5.259,-0.311,0],"ti":[-4.076,0.351,0]},{"i":{"x":0.833,"y":0.877},"o":{"x":0.167,"y":0.205},"t":36,"s":[33.589,-26.081,0],"to":[4.076,-0.351,0],"ti":[-2.176,0.769,0]},{"i":{"x":0.833,"y":0.823},"o":{"x":0.167,"y":0.26},"t":42,"s":[43.479,-27.59,0],"to":[2.176,-0.769,0],"ti":[0.045,1.169,0]},{"i":{"x":0.833,"y":0.758},"o":{"x":0.167,"y":0.157},"t":48,"s":[46.647,-30.693,0],"to":[-0.045,-1.169,0],"ti":[1.933,1.661,0]},{"i":{"x":0.833,"y":0.801},"o":{"x":0.167,"y":0.127},"t":54,"s":[43.206,-34.603,0],"to":[-1.933,-1.661,0],"ti":[3.22,2.434,0]},{"i":{"x":0.833,"y":0.822},"o":{"x":0.167,"y":0.143},"t":60,"s":[35.047,-40.659,0],"to":[-3.22,-2.434,0],"ti":[4.489,1.799,0]},{"i":{"x":0.833,"y":0.819},"o":{"x":0.167,"y":0.157},"t":66,"s":[23.888,-49.205,0],"to":[-4.489,-1.799,0],"ti":[5.632,-0.44,0]},{"i":{"x":0.833,"y":0.826},"o":{"x":0.167,"y":0.155},"t":72,"s":[8.113,-51.451,0],"to":[-5.632,0.44,0],"ti":[5.909,-2.578,0]},{"i":{"x":0.833,"y":0.833},"o":{"x":0.167,"y":0.16},"t":78,"s":[-9.903,-46.568,0],"to":[-5.909,2.578,0],"ti":[5.348,-4.138,0]},{"i":{"x":0.833,"y":0.841},"o":{"x":0.167,"y":0.167},"t":84,"s":[-27.344,-35.983,0],"to":[-5.348,4.138,0],"ti":[4.239,-4.907,0]},{"i":{"x":0.833,"y":0.852},"o":{"x":0.167,"y":0.175},"t":90,"s":[-41.988,-21.737,0],"to":[-4.239,4.907,0],"ti":[3.056,-4.611,0]},{"i":{"x":0.833,"y":0.873},"o":{"x":0.167,"y":0.19},"t":96,"s":[-52.776,-6.544,0],"to":[-3.056,4.611,0],"ti":[1.893,-3.182,0]},{"i":{"x":0.833,"y":0.88},"o":{"x":0.167,"y":0.242},"t":102,"s":[-60.322,5.927,0],"to":[-1.893,3.182,0],"ti":[0.894,-0.787,0]},{"i":{"x":0.833,"y":0.726},"o":{"x":0.167,"y":0.274},"t":108,"s":[-64.136,12.548,0],"to":[-0.894,0.787,0],"ti":[-0.56,1.284,0]},{"i":{"x":0.833,"y":0.833},"o":{"x":0.167,"y":0.12},"t":114,"s":[-65.688,10.648,0],"to":[0.56,-1.284,0],"ti":[-0.819,0.968,0]},{"t":120,"s":[-60.776,4.842,0]}],"ix":2,"l":2},"a":{"a":0,"k":[0,0,0],"ix":1,"l":2},"s":{"a":0,"k":[100,100,100],"ix":6,"l":2}},"ao":0,"ef":[{"ty":5,"nm":"wiggle_01","np":3,"mn":"ADBE Slider Control","ix":1,"en":1,"ef":[{"ty":0,"nm":"Slider","mn":"ADBE Slider Control-0001","ix":1,"v":{"a":0,"k":0.6,"ix":1}}]},{"ty":5,"nm":"wiggle_02","np":3,"mn":"ADBE Slider Control","ix":2,"en":1,"ef":[{"ty":0,"nm":"Slider","mn":"ADBE Slider Control-0001","ix":1,"v":{"a":0,"k":160,"ix":1}}]}],"shapes":[{"ty":"gr","it":[{"d":1,"ty":"el","s":{"a":0,"k":[836,836],"ix":2},"p":{"a":0,"k":[0,0],"ix":3},"nm":"Ellipse Path 1","mn":"ADBE Vector Shape - Ellipse","hd":false},{"ty":"gf","o":{"a":0,"k":100,"ix":10},"r":1,"bm":0,"g":{"p":7,"k":{"a":0,"k":[0,0.514,0.569,0.922,0.165,0.449,0.514,0.939,0.33,0.384,0.459,0.957,0.495,0.275,0.441,0.938,0.66,0.166,0.422,0.92,0.83,0.434,0.572,0.91,1,0.702,0.722,0.9,0,0.2,0.165,0.5,0.33,0.8,0.495,0.8,0.66,0.8,0.83,0.9,1,1],"ix":9}},"s":{"a":0,"k":[-540,0],"ix":5},"e":{"a":0,"k":[540,0],"ix":6},"t":1,"nm":"Gradient Fill 1","mn":"ADBE Vector Graphic - G-Fill","hd":false},{"ty":"tr","p":{"a":0,"k":[0,0],"ix":2},"a":{"a":0,"k":[0,0],"ix":1},"s":{"a":0,"k":[100,100],"ix":3},"r":{"a":0,"k":0,"ix":6},"o":{"a":0,"k":100,"ix":7},"sk":{"a":0,"k":0,"ix":4},"sa":{"a":0,"k":0,"ix":5},"nm":"Transform"}],"nm":"Ellipse 1","np":2,"cix":2,"bm":0,"ix":1,"mn":"ADBE Vector Group","hd":false}],"ip":0,"op":300,"st":0,"bm":0},{"ddd":0,"ind":10,"ty":3,"nm":"control_04","sr":1,"ks":{"o":{"a":0,"k":0,"ix":11},"r":{"a":0,"k":0,"ix":10},"p":{"a":0,"k":[94,1408,0],"ix":2,"l":2},"a":{"a":0,"k":[0,0,0],"ix":1,"l":2},"s":{"a":0,"k":[100,100,100],"ix":6,"l":2}},"ao":0,"ip":0,"op":300,"st":0,"bm":0},{"ddd":0,"ind":11,"ty":4,"nm":"circle_04","parent":10,"sr":1,"ks":{"o":{"a":0,"k":80,"ix":11},"r":{"a":0,"k":0,"ix":10},"p":{"a":1,"k":[{"i":{"x":0.833,"y":0.816},"o":{"x":0.167,"y":0.167},"t":0,"s":[24.523,-85.172,0],"to":[-1.114,3.107,0],"ti":[1.931,-7.026,0]},{"i":{"x":0.833,"y":0.838},"o":{"x":0.167,"y":0.152},"t":6,"s":[17.837,-66.533,0],"to":[-1.931,7.026,0],"ti":[1.158,-7.66,0]},{"i":{"x":0.833,"y":0.848},"o":{"x":0.167,"y":0.172},"t":12,"s":[12.934,-43.013,0],"to":[-1.158,7.66,0],"ti":[0.086,-6.801,0]},{"i":{"x":0.833,"y":0.857},"o":{"x":0.167,"y":0.185},"t":18,"s":[10.887,-20.574,0],"to":[-0.086,6.801,0],"ti":[-1.154,-5.052,0]},{"i":{"x":0.833,"y":0.853},"o":{"x":0.167,"y":0.2},"t":24,"s":[12.416,-2.207,0],"to":[1.154,5.052,0],"ti":[-2.374,-2.687,0]},{"i":{"x":0.833,"y":0.819},"o":{"x":0.167,"y":0.193},"t":30,"s":[17.81,9.739,0],"to":[2.374,2.687,0],"ti":[-3.303,-0.026,0]},{"i":{"x":0.833,"y":0.874},"o":{"x":0.167,"y":0.155},"t":36,"s":[26.662,13.916,0],"to":[3.303,0.026,0],"ti":[-2.716,1.113,0]},{"i":{"x":0.833,"y":0.85},"o":{"x":0.167,"y":0.247},"t":42,"s":[37.631,9.893,0],"to":[2.716,-1.113,0],"ti":[-0.535,-0.243,0]},{"i":{"x":0.833,"y":0.734},"o":{"x":0.167,"y":0.187},"t":48,"s":[42.96,7.236,0],"to":[0.535,0.243,0],"ti":[1.553,-1.966,0]},{"i":{"x":0.833,"y":0.809},"o":{"x":0.167,"y":0.121},"t":54,"s":[40.839,11.35,0],"to":[-1.553,1.966,0],"ti":[3.009,-2.637,0]},{"i":{"x":0.833,"y":0.861},"o":{"x":0.167,"y":0.148},"t":60,"s":[33.64,19.032,0],"to":[-3.009,2.637,0],"ti":[3.11,-2.139,0]},{"i":{"x":0.833,"y":0.876},"o":{"x":0.167,"y":0.207},"t":66,"s":[22.784,27.172,0],"to":[-3.11,2.139,0],"ti":[1.891,-0.519,0]},{"i":{"x":0.833,"y":0.739},"o":{"x":0.167,"y":0.252},"t":72,"s":[14.981,31.868,0],"to":[-1.891,0.519,0],"ti":[0.483,1.858,0]},{"i":{"x":0.833,"y":0.758},"o":{"x":0.167,"y":0.122},"t":78,"s":[11.441,30.286,0],"to":[-0.483,-1.858,0],"ti":[-0.78,4.573,0]},{"i":{"x":0.833,"y":0.807},"o":{"x":0.167,"y":0.127},"t":84,"s":[12.085,20.72,0],"to":[0.78,-4.573,0],"ti":[-1.575,6.887,0]},{"i":{"x":0.833,"y":0.834},"o":{"x":0.167,"y":0.147},"t":90,"s":[16.124,2.851,0],"to":[1.575,-6.887,0],"ti":[-1.423,7.863,0]},{"i":{"x":0.833,"y":0.84},"o":{"x":0.167,"y":0.167},"t":96,"s":[21.536,-20.605,0],"to":[1.423,-7.863,0],"ti":[-0.698,7.615,0]},{"i":{"x":0.833,"y":0.856},"o":{"x":0.167,"y":0.174},"t":102,"s":[24.664,-44.328,0],"to":[0.698,-7.615,0],"ti":[-0.414,6.322,0]},{"i":{"x":0.833,"y":0.894},"o":{"x":0.167,"y":0.198},"t":108,"s":[25.721,-66.293,0],"to":[0.414,-6.322,0],"ti":[0.2,3.146,0]},{"i":{"x":0.833,"y":0.833},"o":{"x":0.167,"y":0.389},"t":114,"s":[27.149,-82.257,0],"to":[-0.2,-3.146,0],"ti":[0.438,0.486,0]},{"t":120,"s":[24.523,-85.172,0]}],"ix":2,"l":2},"a":{"a":0,"k":[618,333,0],"ix":1,"l":2},"s":{"a":0,"k":[100,100,100],"ix":6,"l":2}},"ao":0,"ef":[{"ty":5,"nm":"wiggle_01","np":3,"mn":"ADBE Slider Control","ix":1,"en":1,"ef":[{"ty":0,"nm":"Slider","mn":"ADBE Slider Control-0001","ix":1,"v":{"a":0,"k":0.6,"ix":1}}]},{"ty":5,"nm":"wiggle_02","np":3,"mn":"ADBE Slider Control","ix":2,"en":1,"ef":[{"ty":0,"nm":"Slider","mn":"ADBE Slider Control-0001","ix":1,"v":{"a":0,"k":120,"ix":1}}]}],"shapes":[{"ty":"gr","it":[{"d":1,"ty":"el","s":{"a":0,"k":[460,460],"ix":2},"p":{"a":0,"k":[0,0],"ix":3},"nm":"Ellipse Path 1","mn":"ADBE Vector Shape - Ellipse","hd":false},{"ty":"fl","c":{"a":0,"k":[0.513725490196,0.56862745098,0.921568627451,1],"ix":4},"o":{"a":0,"k":100,"ix":5},"r":1,"bm":0,"nm":"Fill 1","mn":"ADBE Vector Graphic - Fill","hd":false},{"ty":"tr","p":{"a":0,"k":[618,333],"ix":2},"a":{"a":0,"k":[0,0],"ix":1},"s":{"a":0,"k":[100,100],"ix":3},"r":{"a":0,"k":0,"ix":6},"o":{"a":0,"k":100,"ix":7},"sk":{"a":0,"k":0,"ix":4},"sa":{"a":0,"k":0,"ix":5},"nm":"Transform"}],"nm":"Ellipse 1","np":2,"cix":2,"bm":0,"ix":1,"mn":"ADBE Vector Group","hd":false}],"ip":0,"op":300,"st":0,"bm":0},{"ddd":0,"ind":12,"ty":3,"nm":"control_03","sr":1,"ks":{"o":{"a":0,"k":0,"ix":11},"r":{"a":0,"k":0,"ix":10},"p":{"a":0,"k":[360,1538,0],"ix":2,"l":2},"a":{"a":0,"k":[0,0,0],"ix":1,"l":2},"s":{"a":0,"k":[100,100,100],"ix":6,"l":2}},"ao":0,"ip":0,"op":300,"st":0,"bm":0},{"ddd":0,"ind":13,"ty":4,"nm":"circle_03","parent":12,"sr":1,"ks":{"o":{"a":0,"k":100,"ix":11},"r":{"a":0,"k":70,"ix":10},"p":{"s":true,"x":{"a":0,"k":0,"ix":3},"y":{"a":1,"k":[{"i":{"x":[0.65],"y":[1]},"o":{"x":[0.35],"y":[0]},"t":0,"s":[20]},{"i":{"x":[0.65],"y":[1]},"o":{"x":[0.35],"y":[0]},"t":30,"s":[-60]},{"i":{"x":[0.65],"y":[1]},"o":{"x":[0.35],"y":[0]},"t":60,"s":[20]},{"i":{"x":[0.65],"y":[1]},"o":{"x":[0.35],"y":[0]},"t":90,"s":[-60]},{"t":120,"s":[20]}],"ix":4}},"a":{"a":0,"k":[618,333,0],"ix":1,"l":2},"s":{"a":0,"k":[100,100,100],"ix":6,"l":2}},"ao":0,"shapes":[{"ty":"gr","it":[{"d":1,"ty":"el","s":{"a":0,"k":[2142,2142],"ix":2},"p":{"a":0,"k":[0,0],"ix":3},"nm":"Ellipse Path 1","mn":"ADBE Vector Shape - Ellipse","hd":false},{"ty":"gf","o":{"a":0,"k":100,"ix":10},"r":1,"bm":0,"g":{"p":5,"k":{"a":0,"k":[0,1,1,1,0.125,0.667,0.667,0.986,0.25,0.333,0.333,0.973,0.437,0.255,0.276,0.9,0.625,0.176,0.22,0.827,0,0,0.125,0.45,0.25,0.9,0.437,0.95,0.625,1,0.812,1,1,1],"ix":9}},"s":{"a":0,"k":[-1240,0],"ix":5},"e":{"a":0,"k":[940,0],"ix":6},"t":1,"nm":"Gradient Fill 1","mn":"ADBE Vector Graphic - G-Fill","hd":false},{"ty":"tr","p":{"a":0,"k":[618,333],"ix":2},"a":{"a":0,"k":[0,0],"ix":1},"s":{"a":0,"k":[100,100],"ix":3},"r":{"a":0,"k":0,"ix":6},"o":{"a":0,"k":100,"ix":7},"sk":{"a":0,"k":0,"ix":4},"sa":{"a":0,"k":0,"ix":5},"nm":"Transform"}],"nm":"Ellipse 1","np":2,"cix":2,"bm":0,"ix":1,"mn":"ADBE Vector Group","hd":false}],"ip":0,"op":300,"st":0,"bm":0}]}],"layers":[{"ddd":0,"ind":1,"ty":0,"nm":"BG_Effect_Lottie_Android","refId":"comp_0","sr":1,"ks":{"o":{"a":0,"k":100,"ix":11},"r":{"a":0,"k":0,"ix":10},"p":{"a":0,"k":[187.5,325,0],"ix":2,"l":2},"a":{"a":0,"k":[375,650,0],"ix":1,"l":2},"s":{"a":0,"k":[50,50,100],"ix":6,"l":2}},"ao":0,"w":750,"h":1300,"ip":0,"op":120,"st":0,"bm":0}],"markers":[]}